<?xml version='1.0' encoding='utf8'?><data><item><title>Près de 7.000 cas de tuberculose dépistés en 2022 au Kongo-Central Ouest</title><link>https://acpcongo.com/index.php/2023/03/30/pres-de-7-000-cas-de-tuberculose-depistes-en-2022-au-kongo-central-ouest/</link><ns0keywords>kongo-central ouest,médecin coordonnateur,cas de tuberculose,ambroise umba mbuzi,tuberculose dépistés,province,matadi,dépistés en 2022,7.000 cas,2022 au kongo-central,genex pert,mars 2023 acp,district du bas-fleuve</ns0keywords><pubDate>Fri, 31 Mar 2023 01:27:00 +0200</pubDate><guid isPermaLink="false">acpcongo-7f931de0c9fc8f8bb2a8adbe55ecc7ef</guid><source country="CD" url="https://acpcongo.com/index.php/feed/">acpcongo</source><ns1language>fr</ns1language><category>Tuberculosis</category><category ns0trigger="lèpre[1]; ">Leprosy</category><ns0entity id="2082114" name="ACP">ACP</ns0entity><georss>-5.83861 13.46306</georss></item><item><title>Argentine Cup: Belgrano in La Rioja</title><link>https://www.archyde.com/argentine-cup-belgrano-in-la-rioja/</link><ns0keywords>argentine cup,date,la rioja,augusto mercado luna,belgrano in la,belgrano will play,vargas stadium,rivadavia de mendoza,domingo,secretary of sports,independiente rivadavia de</ns0keywords><pubDate>Fri, 31 Mar 2023 01:23:00 +0200</pubDate><guid isPermaLink="false">archyde-a6b04eeb40cb4f2f8395a3d4dbd28f51</guid><source country="US" url="https://www.archyde.com/">archyde</source><ns1language>en</ns1language><category ns0trigger="Lepra[1]; ">Leprosy</category><ns0entity id="1896121" name="Professional League">Professional League</ns0entity><ns0entity id="861188" name="Carlos Augusto">Carlos Augusto</ns0entity><ns0entity id="2181659" name="Rivadavia de Mendoza">Rivadavia de Mendoza</ns0entity><georss>-29.41105 -66.85067</georss></item><item><title>Copa Argentina: Belgrano en La Rioja</title><link>https://www.lavoz.com.ar/deportes/futbol/copa-argentina-belgrano-en-la-rioja/</link><ns0keywords>copa argentina,volverá a jugar,rioja,rivadavia de mendoza,augusto mercado luna,estadio carlos augusto,miércoles 26,secretaria de deportes,llamado estadio vargas,independiente rivadavia,belgrano,32avos,fecha,abril ante independiente</ns0keywords><pubDate>Fri, 31 Mar 2023 01:19:00 +0200</pubDate><guid isPermaLink="false">lavoz-52ba99c48fe1d2eaeb9e83b4fcb1278a</guid><source country="AR" url="https://www.lavoz.com.ar/">lavoz</source><ns1language>es</ns1language><category ns0trigger="Lepra[1]; ">Leprosy</category><ns0entity id="861188" name="Carlos Augusto">Carlos Augusto</ns0entity><ns0entity id="2181659" name="Rivadavia de Mendoza">Rivadavia de Mendoza</ns0entity><georss>-34.56270 -58.45829</georss></item><item><title>Luciano Abecasis, un jugador clave para Independiente Rivadavia</title><link>https://www.diariouno.com.ar/ovacion/futbol/luciano-abecasis-un-jugador-clave-independiente-rivadavia-n1087300</link><ns0keywords>independiente rivadavia,luciano abecasis,jugador clave,deportivo riestra,sector defensivo,racing de córdoba,clave para independiente,t ambién,interesar ever demaldé,partidos y t,santiago moya,ganar los partidos,jugará este domingo,contundencia para ganar</ns0keywords><pubDate>Fri, 31 Mar 2023 01:08:00 +0200</pubDate><guid isPermaLink="false">diariouno-d215c8bc980da8b6221c8700b4165bfb</guid><source country="AR" url="https://www.diariouno.com.ar">diariouno</source><ns1language>es</ns1language><category ns0trigger="Lepra[1]; ">Leprosy</category><ns0entity id="3097583" name="Deportivo Riestra">Deportivo Riestra</ns0entity><ns0entity id="2125986" name="Luciano Abecasis">Luciano Abecasis</ns0entity><ns0entity id="3068818" name="Racing de Córdoba">Racing de Córdoba</ns0entity><georss>-24.18552 -62.88535</georss></item><item><title>San+Luis</title><link>https://www.cadena3.com/Pagina/tag?q=San+Luis</link><ns0keywords>concejo municipal,calle san luis,comerciantes de calle,cadena 3,alberto rodríguez saá,ámbito del concejo,juan manuel casella,vuelve a discutirse,honda type,villa mercedes,san luis habló,restringir la movilidad,diego gatica</ns0keywords><pubDate>Thu, 30 Mar 2023 18:53:00 +0200</pubDate><guid isPermaLink="false">cadena3-ac43e4d73c822fe22d41c28ddc010d6b</guid><source country="AR" url="http://www.cadena3.com">cadena3</source><ns1language>es</ns1language><category ns0trigger="Lepra[2]; ">Leprosy</category><ns0entity id="13280" name="Grand Prix">Gran Premio</ns0entity><ns0entity id="725582" name="Alberto Rodriguez Saa">Alberto Rodríguez Saá</ns0entity><ns0entity id="3043147" name="Manuel Urcera">Manuel Urcera</ns0entity><ns0entity id="2210278" name="Miguel Vega">Miguel Vega</ns0entity><ns0entity id="656550" name="Juan Manuel Casella">Juan Manuel Casella</ns0entity><ns0entity id="162094" name="Alberto Rodriguez">Alberto Rodríguez</ns0entity><ns0entity id="2008816" name="Mariano Werner">Mariano Werner</ns0entity><ns0entity id="3179972" name="Diego Gatica">Diego Gatica</ns0entity><ns0entity id="3055736" name="Santiago Mangoni">Santiago Mangoni</ns0entity><ns0entity id="106105" name="Juan Cruz">Juan Cruz</ns0entity><ns0entity id="2349178" name="José Manuel Urcera">José Manuel Urcera</ns0entity><ns0entity id="2929399" name="Willer Ditta">Willer Ditta</ns0entity><ns0entity id="1548747" name="Manuel Casella">Manuel Casella</ns0entity><ns0entity id="265144" name="Claudio Poggi">Claudio Poggi</ns0entity><ns0entity id="2887442" name="Guadalupe Belén Lucero">Guadalupe Belén Lucero</ns0entity><georss>-33.29501 -66.33563</georss></item><item><title>Hemonúcleo de Foz do Iguaçu pede para que doadores de sangue agendem horário para otimizar serviço; veja como</title><link>https://g1.globo.com/pr/oeste-sudoeste/noticia/2023/03/30/hemonucleo-de-foz-do-iguacu-pede-para-que-doadores-de-sangue-agendem-horario-para-otimizar-servico-veja-como.ghtml</link><ns0keywords>sangue agendem horário,otimizar serviço,foz do iguaçu,hemonúcleo de foz,antecedem a doação,iguaçu pede,horário para otimizar,dias após melhora,melhora dos sintomas,doadores de sangue,carteira nacional,condições de saúde,apresentar documento oficial,veja,aguardar</ns0keywords><pubDate>Thu, 30 Mar 2023 16:23:00 +0200</pubDate><guid isPermaLink="false">g1-globo-e7aa02d95234baba6fd107c0e1789de3</guid><source country="BR" url="http://g1.globo.com/dynamo/rss2.xml">g1-globo</source><ns1language>pt</ns1language><category>BodyModificationImplant</category><category ns0trigger="Hanseníase[1]; ">Leprosy</category><category>Viralhepatitis</category><category>AIDS-HIV</category><category>ImplantsAdverseEffects</category><georss>-25.54778 -54.58806</georss></item><item><title>White gold from Black hands: the Gullah Geechee fight for a legacy after slavery | DeNeen L Brown</title><link>https://www.theguardian.com/news/ng-interactive/2023/mar/30/white-gold-from-black-hands-the-gullah-geechee-fight-for-a-legacy-after-slavery-manchester</link><ns0keywords>sea island cotton,enslaved africans,gullah geechee people,hilton head island,white gold,deneen l brown,sold,gunn,hands,campbell</ns0keywords><pubDate>Thu, 30 Mar 2023 13:15:00 +0200</pubDate><guid isPermaLink="false">guardian-8c950df92f1b9b4aea278c5359626459</guid><source country="GB" url="https://www.theguardian.com/international/rss">guardian</source><ns1language>en</ns1language><category ns0trigger="leprosy[1]; ">Leprosy</category><ns0entity id="1606268" name="Valley State University">Valley State University</ns0entity><ns0entity id="408224" name="Richard Reynolds">Richard Reynolds</ns0entity><ns0entity id="2228073" name="Sarah Parker">Sarah Parker</ns0entity><ns0entity id="1628240" name="Statue of Liberty">Statue of Liberty</ns0entity><ns0entity id="1801" name="Wall Street">Wall Street</ns0entity><ns0entity id="11665" name="Martin Luther King">Martin Luther King</ns0entity><ns0entity id="11665" name="Martin Luther King">Martin Luther King Jr</ns0entity><ns0entity id="2266836" name="New York Tribune">New York Tribune</ns0entity><ns0entity id="2386354" name="Henry Hammond">Henry Hammond</ns0entity><ns0entity id="40694" name="Susan Williams">Susan Williams</ns0entity><ns0entity id="57367" name="Martin Luther">Martin Luther</ns0entity><ns0entity id="2675600" name="Pierce Butler">Pierce Butler</ns0entity><ns0entity id="70970" name="The Guardian">The Guardian</ns0entity><ns0entity id="155198" name="Jim Crow">Jim Crow</ns0entity><ns0entity id="575990" name="James Henry">James Henry</ns0entity><georss>32.08354 -81.09983</georss></item><item><title>Togo Could Move the Needle on Tropical Diseases</title><link>https://iafrica.com/togo-could-move-the-needle-on-tropical-diseases/</link><ns0keywords>needle on tropical,move the needle,neglected tropical diseases,togo could move,africa,tropical regions,skin,group of 20,evidence,infections,20 diseases found,study</ns0keywords><pubDate>Thu, 30 Mar 2023 07:18:00 +0200</pubDate><guid isPermaLink="false">iafrica-a91aa96c6c9388e5ab648dbce1db5f64</guid><source country="ZA" url="https://www.iafrica.com/feed/">iafrica</source><ns1language>en</ns1language><category>WHO</category><category ns0trigger="leprosy[1]; ">Leprosy</category><category>ArtificialTissuesAdverseEffects</category><ns0entity id="22487" name="World Health Organization">WHO</ns0entity><georss>6.12874 1.22154</georss></item><item><title>HEALTH18 mins ago 7,806 cases recorded in TB epidemic in Bauchi</title><link>https://www.nationallightngr.com/2023/03/30/7806-cases-recorded-in-tb-epidemic-in-bauchi/</link><ns0keywords>world tuberculosis day,tb epidemic,recorded in tb,bauchi state agency,mins ago 7,806,world health organisation,health18 mins ago,leprosy and malaria,erupted in bauchi,epidemic in bauchi,sani mohammad,end,ago 7,806 cases</ns0keywords><pubDate>Thu, 30 Mar 2023 06:26:00 +0200</pubDate><guid isPermaLink="false">nationallightngr-b800dd1d62e7df08830f028fb1e1f93e</guid><source country="NE" url="https://www.nationallightngr.com/category/events/">nationallightngr</source><ns1language>en</ns1language><category>Epidemic</category><category>AIDS-HIV</category><category>Tuberculosis</category><category>WHO</category><category ns0trigger="Leprosy[1]; ">Leprosy</category><ns0entity id="2090589" name="State Agency">State Agency</ns0entity><ns0entity id="22487" name="World Health Organization">World Health Organisation</ns0entity><ns0entity id="22487" name="World Health Organization">WHO</ns0entity><ns0entity id="134782" name="Prophet Muhammad">Mohammad</ns0entity><ns0entity id="53103" name="Health Organisation">Health Organisation</ns0entity><georss>10.31032 9.84388</georss></item><item><title>JCM, Vol. 12, Pages 2596: Association of a Novel Homozygous Variant in ABCA1 Gene with Tangier Disease</title><link>https://www.mdpi.com/2077-0383/12/7/2596</link><ns0keywords>homozygous variant,jcm,vol,tangier disease,abca1 gene,lipoprotein cholesterol hdl-c,high-density lipoprotein cholesterol,patient,pages 2596,case study,variant in abca1,figure</ns0keywords><pubDate>Thu, 30 Mar 2023 05:54:00 +0200</pubDate><guid isPermaLink="false">mdpi-7b14ea9ae4559c90b47addb64a4bbce6</guid><source country="CH" url="https://www.mdpi.com/rss">mdpi</source><ns1language>en</ns1language><category ns0trigger="leprosy[1]; ">Leprosy</category><category>BloodProducts</category><category>BloodProductsAdverseEffects</category><georss>35.76727 -5.79975</georss></item><item><title>In full bloom</title><link>https://www.mid-day.com/mumbai-guide/things-to-do/article/in-full-bloom-23278106</link><ns0keywords>full bloom,natural history society,kiran thumma,officer at bombay,witness several blooming,bnhs cec,time to witness,pollinating flowers,plant,perfect time,maharashtra nature park,evolve into fruits,summer flower trail</ns0keywords><pubDate>Thu, 30 Mar 2023 05:34:00 +0200</pubDate><guid isPermaLink="false">mid-day-9b1ab706a4d53070926348d72c0ef9ec</guid><source country="IN" url="https://www.mid-day.com/search/Coronavirus-all">mid-day</source><ns1language>en</ns1language><category ns0trigger="leprosy[1]; ">Leprosy</category><ns0entity id="1007627" name="Sanjay Gandhi">Sanjay Gandhi</ns0entity><ns0entity id="2507357" name="Natural History">Natural History</ns0entity><georss>19.07283 72.88261</georss></item><item><title>Qué dijo Heinze sobre la posible llegada de Martino a Boca</title><link>https://www.mdzol.com/deportes/2023/3/29/la-fuerte-respuesta-de-heinze-sobre-la-posible-llegada-de-martino-boca-si-alguien-quiere-ensuciar-325986.html</link><ns0keywords>hugo ibarra,heinze,copa libertadores,tata martino,martino a boca,llegada de martino,timón y despidió,boca noticias relacionadas,lepra,ibarra a días,decisión,selección argentina,golpe de timón,newell's,días del debut</ns0keywords><pubDate>Wed, 29 Mar 2023 23:06:00 +0200</pubDate><guid isPermaLink="false">mdzol-c8a821cee223a326a76d7b81948b4c43</guid><source country="AR" url="https://www.mdzol.com/">mdzol</source><ns1language>es</ns1language><category ns0trigger="Lepra[3]; ">Leprosy</category><ns0entity id="243490" name="Gerardo Martino">Gerardo Martino</ns0entity><ns0entity id="28867" name="Hugo Ibarra">Hugo Ibarra</ns0entity><ns0entity id="17851" name="Gabriel Heinze">Gabriel Heinze</ns0entity><ns0entity id="932914" name="Tata Martino">Tata Martino</ns0entity><georss>-34.61315 -58.37723</georss></item><item><title>Pacientes com hanseníase que vivem em casa de saúde vão trocar cesta básica por cartão alimentação em Ubá</title><link>https://g1.globo.com/mg/zona-da-mata/noticia/2023/03/29/pacientes-com-hanseniase-que-vivem-em-casa-de-saude-vao-trocar-cesta-basica-por-cartao-alimentacao-em-uba.ghtml</link><ns0keywords>casa de saúde,trocar cesta básica,saúde padre damião,alimentação em ubá,pacientes com hanseníase,hanseníase que vivem,cartão alimentação,vivem em casa,minas gerais,saúde vão trocar,fundação hospitalar</ns0keywords><pubDate>Wed, 29 Mar 2023 21:31:00 +0200</pubDate><guid isPermaLink="false">g1-globo-6cc6ed111297fbf13b09a8f51f878409</guid><source country="BR" url="http://g1.globo.com/dynamo/rss2.xml">g1-globo</source><ns1language>pt</ns1language><category ns0trigger="hanseníase[4]; ">Leprosy</category><ns0entity id="633080" name="Jose Nascimento">José Nascimento</ns0entity><ns0entity id="1808054" name="Damiao Jose">Damião, José</ns0entity><georss>-34.37589 -55.23771</georss></item><item><title>Gerardo Martino, el elegido por Riquelme que las vivió todas y al que le falta el desafío de dirigir a Boca</title><link>https://www.clarin.com/deportes/gerardo-martino-elegido-riquelme-vivio-todas-falta-desafio-dirigir-boca_0_IY7jx1zu3N.html</link><ns0keywords>tata,elegido por riquelme,selección argentina,gerardo martino,dirigir a boca,falta el desafío,cerro porteño,ruso jorge ribolzi,trabajo en paraguay,desafío de dirigir,clubes como libertad,presidente mauricio macri</ns0keywords><pubDate>Wed, 29 Mar 2023 21:02:00 +0200</pubDate><guid isPermaLink="false">clarin-c8cbc7b9f892541f5437306cde53ca7b</guid><source country="AR" url="https://www.clarin.com/rss/lo-ultimo/">clarin</source><ns1language>es</ns1language><category ns0trigger="Lepra[2]; ">Leprosy</category><ns0entity id="243490" name="Gerardo Martino">Gerardo Martino</ns0entity><ns0entity id="892811" name="2010 FIFA World Cup">Mundial 2010</ns0entity><ns0entity id="53734" name="Julio Grondona">Julio Grondona</ns0entity><ns0entity id="2811021" name="Carlos Picerni">Carlos Picerni</ns0entity><ns0entity id="2284008" name="El Gráfico">El Gráfico</ns0entity><ns0entity id="145836" name="Mauricio Macri">Mauricio Macri</ns0entity><ns0entity id="14322" name="America s Cup">Copa América</ns0entity><ns0entity id="2336433" name="Cholo Simeone">Cholo Simeone</ns0entity><ns0entity id="3507" name="Marcelo Bielsa">Marcelo Bielsa</ns0entity><ns0entity id="841595" name="Tito Vilanova">Tito Vilanova</ns0entity><ns0entity id="66075" name="Lionel Messi">Messi</ns0entity><ns0entity id="66075" name="Lionel Messi">Lionel Messi</ns0entity><ns0entity id="29210" name="Real Madrid">Real Madrid</ns0entity><ns0entity id="533813" name="Cerro Porteno">Cerro Porteño</ns0entity><ns0entity id="327354" name="Alejandro Sabella">Alejandro Sabella</ns0entity><georss>-25.28646 -57.64700</georss></item><item><title>Quel parent peut bénéficier du nouveau congé pour enfant atteint d’une maladie chronique ou d’un cancer</title><link>https://www.capital.fr/economie-politique/quel-parent-peut-beneficier-du-nouveau-conge-pour-enfant-atteint-dune-maladie-chronique-ou-dun-cancer-1464343</link><ns0keywords>d'une maladie chronique,enfant atteint d'une,bénéficier d'un congé,parent peut bénéficier,grave,nouveau congé,découverte d'un cancer,affections,rappelle previssima,congé pour enfant,nécessitant un traitement,chronique ou d'un,bénéficier du nouveau</ns0keywords><pubDate>Wed, 29 Mar 2023 17:55:00 +0200</pubDate><guid isPermaLink="false">capital-FR-a05f86ad00d845fbc6e4f2a9db1c7d16</guid><source country="FR" url="https://www.capital.fr/rss">capital-FR</source><ns1language>fr</ns1language><category ns0trigger="lèpre[1]; ">Leprosy</category><category>Schistosomiasis</category></item><item><title>The invisible ones Give the fishing rod, but not the fishes</title><link>https://www.meer.com/en/8630-the-invisible-ones</link><ns0keywords>vimala dermatological center,fishing rod,leprosy,invisible ones give,give the fishing,hospital,children,lucia,fishes,people,lives which leave,leave me wonderstruck,affected</ns0keywords><pubDate>Wed, 29 Mar 2023 16:32:00 +0200</pubDate><guid isPermaLink="false">wsimag-cd30ff99861a8c785b1bb9e4422af7e1</guid><source country="IT" url="https://wsimag.com/">wsimag</source><ns1language>en</ns1language><category ns0trigger="leprosy[10]; ">Leprosy</category><ns0entity id="11844" name="Dominique Lapierre">Dominique Lapierre</ns0entity><ns0entity id="15927" name="Teresa de Calcuta">Mother Teresa</ns0entity><ns0entity id="1215333" name="Hildegard von Bingen">Hildegard of Bingen</ns0entity><ns0entity id="263038" name="Juan Ines de la Cruz">Juana Inés de la Cruz</ns0entity><georss>28.63576 77.22445</georss></item><item><title>Gambia commemorates World ` Tuberculosis Day</title><link>https://thepoint.gm/africa/gambia/national-news/gambia-commemorates-world-tuberculosis-day</link><ns0keywords>gambia commemorates world,day,world health organization,control programme office,tb,global health threat,national leprosy,hope and encourage,made,high level leadership,disease,global challenges,people,encourage high level</ns0keywords><pubDate>Wed, 29 Mar 2023 15:07:00 +0200</pubDate><guid isPermaLink="false">thepoint-6321c8a5bea4e3c70281b78d56002c35</guid><source country="GM" url="https://thepoint.gm/africa/gambia/national-news">thepoint</source><ns1language>en</ns1language><category>Tuberculosis</category><category>CoronavirusInfection</category><category ns0trigger="Leprosy[2]; ">Leprosy</category><category>WHO</category><ns0entity id="3105" name="African Union">African Union</ns0entity><ns0entity id="2468720" name="Ministry of Health">Ministry of Health</ns0entity><ns0entity id="22487" name="World Health Organization">World Health Organization</ns0entity><ns0entity id="22487" name="World Health Organization">WHO</ns0entity><ns0entity id="2528522" name="Coronavirus">covid-19</ns0entity><ns0entity id="2528522" name="Coronavirus">Covid-19</ns0entity><ns0entity id="23951" name="Member States">member states</ns0entity><georss>13.45274 -16.57803</georss></item><item><title>UK defence minister would 'love' return of conscription</title><link>https://guardian.ng/news/uk-defence-minister-would-love-return-of-conscription/</link><ns0keywords>defence secretary ben,britain scrapped national,uk defence minister,minister would love,britain emulate finland,young men,return,defence minister pal,uk defence secretary,briefing reporters alongside,secretary ben wallace,sweden,politicians and media</ns0keywords><pubDate>Wed, 29 Mar 2023 13:46:00 +0200</pubDate><guid isPermaLink="false">guardian-ng-d54012ecda8672b63771be26b843b446</guid><source country="NG" url="https://guardian.ng/category/business-services/">guardian-ng</source><ns1language>en</ns1language><category ns0trigger="leprosy[1]; ">Leprosy</category><ns0entity id="48992" name="Ike Ekweremadu">Ike Ekweremadu</ns0entity><ns0entity id="87141" name="Ben Wallace">Ben Wallace</ns0entity><ns0entity id="338033" name="NATO">NATO</ns0entity><ns0entity id="22724" name="World War">World War</ns0entity><ns0entity id="2292486" name="Lagos State University">Lagos State University</ns0entity><ns0entity id="1817212" name="Pal Jonson">Pal Jonson</ns0entity><ns0entity id="117801" name="Old Bailey">Old Bailey</ns0entity><ns0entity id="218282" name="Hugh Davies">Hugh Davies</ns0entity><ns0entity id="22157" name="Second World War">World War II</ns0entity><ns0entity id="3153309" name="Obinna Obeta">Obinna Obeta</ns0entity><georss>51.50853 -0.12574</georss></item><item><title>Medikamentet, burim i infeksioneve të rrezikshme</title><link>https://konica.al/2019/04/medikamentet-burim-i-infeksioneve-te-rrezikshme/</link><ns0keywords>burim i infeksioneve,infeksioneve të rrezikshme,bakter,medikamentet,abscesit,sëmundjen hansen,abscesi,infeksionit,infektuar,quajtur edhe m,zakonisht,mykobacteriumit i quajtur,mushkërive,i mykobacteriumit i</ns0keywords><pubDate>Wed, 29 Mar 2023 11:41:00 +0200</pubDate><guid isPermaLink="false">konica-a35e1a38bb5ef8e9da4cb21d26b10bda</guid><source country="AL" url="https://konica.al/">konica</source><ns1language>sq</ns1language><category ns0trigger="Leprosy[1]; ">Leprosy</category></item><item><title>Isenção do Imposto de Renda é direito das pessoas portadoras de doenças graves, que podem deixar de pagar e até restituir</title><link>https://www.estadao.com.br/politica/blog-do-fausto-macedo/isencao-do-imposto-de-renda-e-direito-das-pessoas-portadoras-de-doencas-graves-que-podem-deixar-de-pagar-e-ate-restituir/</link><ns0keywords>imposto de renda,doenças graves,portadoras de doenças,deixar de pagar,pessoas portadoras,tribunal de justiça,pansieri advogados,felipe gasparim,renda é direito,ministro humberto martins,isenção do imposto</ns0keywords><pubDate>Wed, 29 Mar 2023 11:08:00 +0200</pubDate><guid isPermaLink="false">estadao-e3c78142645e6aee9cdb7f8a0bfd03cc</guid><source country="BR" url="https://politica.estadao.com.br/">estadao</source><ns1language>pt</ns1language><category ns0trigger="hanseníase[1]; ">Leprosy</category><ns0entity id="2030607" name="Direito Constitucional">Direito Constitucional</ns0entity><ns0entity id="1906857" name="Flavio Pansieri">Flávio Pansieri</ns0entity><ns0entity id="2204794" name="Sergio Kukina">Sérgio Kukina</ns0entity><ns0entity id="657702" name="Humberto Martins">Humberto Martins</ns0entity><georss>-23.54750 -46.63611</georss></item><item><title>Tanzania: At Least 1,000 Diagnosed With TB in Katavi</title><link>https://allafrica.com/stories/202303290107.html</link><ns0keywords>tanzania,katavi region,world health organisation,mpanda district commissioner,diagnosed with tb,tb in katavi,minister kassim majaliwa,1,000 diagnosed,tuberculosis tb,people in mpanda,patients,municipality of katavi</ns0keywords><pubDate>Wed, 29 Mar 2023 09:17:00 +0200</pubDate><guid isPermaLink="false">allafrica-2a3cf12f0e1874b5bbda6dfd00863fd8</guid><source country="US" url="https://allafrica.com/tools/headlines/rdf/eastafrica/headlines.rdf">allafrica</source><ns1language>en</ns1language><category ns0trigger="Leprosy[1]; ">Leprosy</category><category>WHO</category><ns0entity id="2468720" name="Ministry of Health">Ministry of Health</ns0entity><ns0entity id="22487" name="World Health Organization">World Health Organisation</ns0entity><ns0entity id="22487" name="World Health Organization">WHO</ns0entity><ns0entity id="1523545" name="Kassim Majaliwa">Kassim Majaliwa</ns0entity><ns0entity id="53103" name="Health Organisation">Health Organisation</ns0entity><georss>-6.34379 31.06951</georss></item><item><title>MUNI MAYNAS ENTREGÓ ALIMENTOS A ENFERMOS DE HANSEN</title><link>https://proycontra.com.pe/muni-maynas-entrego-alimentos-a-enfermos-de-hansen/</link><ns0keywords>muni maynas entregó,enfermos de hansen,municipalidad provincial,adela esmeralda jiménez,maynas entregó alimentos,división de desarrollo,alimentos a enfermos,entregaron 40 bolsas,diversas actividades basadas,bolsas con productos,alcaldesa adela jiménez,actual gestión,adultos mayores,adela jiménez participó,entregó una bolsa</ns0keywords><pubDate>Wed, 29 Mar 2023 08:35:00 +0200</pubDate><guid isPermaLink="false">proycontra-19affedab7a7c38b78e676b215c0a7c8</guid><source country="PE" url="https://proycontra.com.pe/category/actualidad/">proycontra</source><ns1language>es</ns1language><category ns0trigger="Lepra[1]; ">Leprosy</category><ns0entity id="2957099" name="Adulto Mayor">ADULTO MAYOR</ns0entity><georss>-3.74912 -73.25383</georss></item><item><title>Bauchi Records 7,806 Tuberculosis Cases</title><link>https://leadership.ng/bauchi-records-7806-tuberculosis-cases/</link><ns0keywords>world tuberculosis day,bauchi state ministry,records 7,806 tuberculosis,sabiu abdu gwalabe,bauchi records 7,806,world health organisation,7,806 tuberculosis cases,sani muhammad dambam,year's world tuberculosis,tuberculosis in 2022,confirmed cases,yakubu gida abdullahi,recorded 7,806 confirmed</ns0keywords><pubDate>Wed, 29 Mar 2023 08:17:00 +0200</pubDate><guid isPermaLink="false">leadership-689ee6eceacd3797cfb667caf5a22ab6</guid><source country="NG" url="https://leadership.ng/">leadership</source><ns1language>en</ns1language><category>AIDS-HIV</category><category>Tuberculosis</category><category ns0trigger="Leprosy[1]; ">Leprosy</category><category>WHO</category><ns0entity id="2691160" name="Sani Muhammad">Sani Muhammad</ns0entity><ns0entity id="2090589" name="State Agency">State Agency</ns0entity><ns0entity id="2468720" name="Ministry of Health">Ministry of Health</ns0entity><ns0entity id="22487" name="World Health Organization">World Health Organisation</ns0entity><ns0entity id="22487" name="World Health Organization">WHO</ns0entity><ns0entity id="53103" name="Health Organisation">Health Organisation</ns0entity><georss>10.31032 9.84388</georss></item><item><title>Leprosy, scabies and yaws — Togo’s neglected tropical skin diseases need attention</title><link>https://www.downtoearth.org.in/blog/africa/leprosy-scabies-and-yaws-togo-s-neglected-tropical-skin-diseases-need-attention-88496</link><ns0keywords>togo's neglected tropical,found,leprosy,cent,world health organization,cases,yaws togo's neglected,tropical skin diseases,study,africa,scabies and yaws</ns0keywords><pubDate>Wed, 29 Mar 2023 07:24:00 +0200</pubDate><guid isPermaLink="false">downtoearth-cf5b72c2cc845f0098ca3f4cc89fe96b</guid><source country="IN" url="https://www.downtoearth.org.in/rss/all">downtoearth</source><ns1language>en</ns1language><category>Scabies</category><category>undernutrition</category><category>Onchocerciasis</category><category>Buruliulcer</category><category ns0trigger="leprosy[2]; Leprosy[1]; ">Leprosy</category><category>Filariasis</category><category>Yaws</category><category>WHO</category><category>ArtificialTissuesAdverseEffects</category><ns0entity id="22487" name="World Health Organization">World Health Organization</ns0entity><ns0entity id="22487" name="World Health Organization">WHO</ns0entity><georss>6.12874 1.22154</georss></item><item><title>Boletín de Calificaciones de la goleada de Argentina ante Curazao</title><link>https://www.cadena3.com/noticia/estadio-3-rosario/boletin-de-calificaciones-de-la-goleada-de-argentina-ante-curazao_353768</link><ns0keywords>santiago del estero,funcionamiento del equipo,claudio giglioni analizó,segmento en cadena,analizó el funcionamiento,cadena 3 rosario,boletín de calificaciones,7 a 0,clásico segmento,equipo de russo,vivió otra fiesta,curazao,selección vivió</ns0keywords><pubDate>Wed, 29 Mar 2023 04:57:00 +0200</pubDate><guid isPermaLink="false">cadena3-09a13b0c3da8c63ea0d0b729cde51b60</guid><source country="AR" url="http://www.cadena3.com">cadena3</source><ns1language>es</ns1language><category ns0trigger="Lepra[1]; ">Leprosy</category><ns0entity id="421670" name="FIFA">FIFA</ns0entity><ns0entity id="220486" name="Nicolas Gonzalez">Nicolás González</ns0entity><ns0entity id="66075" name="Lionel Messi">Messi</ns0entity><ns0entity id="1333723" name="Enzo Fernandez">Enzo Fernández</ns0entity><georss>-27.79511 -64.26149</georss></item><item><title>Is the key to anti-aging in YOUR backyard? Common weed shows promise in early study</title><link>https://todayheadline.co/is-the-key-to-anti-aging-in-your-backyard-common-weed-shows-promise-in-early-study/</link><ns0keywords>key to anti-aging,common weed shows,cocklebur fruit,backyard,weed shows promise,myongji university,south korea,promise in early,plant,early study,wound healing,skin,visible aging,native american medicine</ns0keywords><pubDate>Wed, 29 Mar 2023 04:33:00 +0200</pubDate><guid isPermaLink="false">todayheadline-914706d5ae33c11a4fa6e18767a7b45c</guid><source country="US" url="https://todayheadline.co">todayheadline</source><ns1language>en</ns1language><category>Radiationdamage</category><category ns0trigger="leprosy[1]; ">Leprosy</category><ns0entity id="2003159" name="American Society">American Society</ns0entity><georss>22.49471 114.13812</georss></item><item><title>‘26,371 Tuberculosis cases detected in Kano, last year’</title><link>https://guardian.ng/news/26371-tuberculosis-cases-detected-in-kano-last-year/</link><ns0keywords>tuberculosis cases detected,treatment success rate,tuberculosis foundation nigeria,detected in kano,leprosy control programme,26,371 tuberculosis cases,kano state,tb,year,state in 2022,senior programme manager,genexpert diagnostic sites,10-15% are children,mamman bajehson,state records 95%</ns0keywords><pubDate>Wed, 29 Mar 2023 04:14:00 +0200</pubDate><guid isPermaLink="false">guardian-ng-42fc6b2597f4ba3a97829f04a9c63c26</guid><source country="NG" url="https://guardian.ng/">guardian-ng</source><ns1language>en</ns1language><category>Tuberculosis</category><category ns0trigger="Leprosy[1]; ">Leprosy</category><ns0entity id="988552" name="Facebook">Facebook</ns0entity><ns0entity id="70970" name="The Guardian">The Guardian</ns0entity><georss>12.00012 8.51672</georss></item><item><title>Is the key to anti-aging in your backyard? The common weed shows promise in an early study</title><link>https://whatsnew2day.com/is-the-key-to-anti-aging-in-your-backyard-the-common-weed-shows-promise-in-an-early-study/</link><ns0keywords>key to anti-aging,wound healing,plant,skin,cocklebur fruit,common weed shows,ultraviolet light,south korea,collagen production,backyard,weed shows promise,speed up wound,native american medicine,healing in lab</ns0keywords><pubDate>Wed, 29 Mar 2023 01:55:00 +0200</pubDate><guid isPermaLink="false">whatsnew2day-ec156e7733b2d529115228ddf1190c6e</guid><source country="US" url="https://whatsnew2day.com/">whatsnew2day</source><ns1language>en</ns1language><category ns0trigger="leprosy[1]; ">Leprosy</category><ns0entity id="2003159" name="American Society">American Society</ns0entity><georss>22.49471 114.13812</georss></item><item><title>Avoid stigmatising lepers - Fr Campbell urges health personnel</title><link>https://www.graphic.com.gh/news/general-news/avoid-stigmatising-lepers-fr-campbell-urges-health-personnel.html</link><ns0keywords>lepers aid committee,campbell urges health,nii lamptey campbell,leprosy patients,avoid stigmatising lepers,urges health personnel,stigmatising lepers fr,lepers fr campbell,ghana health service,visited health facilities,nurses and doctors,fr campbell urges,train health personnel</ns0keywords><pubDate>Wed, 29 Mar 2023 00:52:00 +0200</pubDate><guid isPermaLink="false">graphic-gh-72809ffadd5ec1d61ea012511c942ec7</guid><source country="GH" url="https://www.graphic.com.gh/news.html">graphic-gh</source><ns1language>en</ns1language><category ns0trigger="leprosy[7]; ">Leprosy</category><ns0entity id="632537" name="Abdallah Banda">Abdallah Banda</ns0entity><ns0entity id="608127" name="Very Rev">Very Rev</ns0entity><ns0entity id="1426914" name="Abd Allāh">Abdallah</ns0entity><ns0entity id="1008517" name="Mahamudu Bawumia">Mahamudu Bawumia</ns0entity><ns0entity id="2209834" name="Ghana Health Service">Ghana Health Service</ns0entity></item><item><title>Namibia 2% short of TB treatment target</title><link>https://informante.web.na/?p=316918</link><ns0keywords>treatment success rate,maria david,world health organisation,tuberculosis preventive therapy,tb treatment target,public health concern,short of tb,namibia 2% short,shangula,strides in addressing</ns0keywords><pubDate>Tue, 28 Mar 2023 22:43:00 +0200</pubDate><guid isPermaLink="false">informante-2444c53aa21c22c40a6f6c30a920244b</guid><source country="NA" url="https://informante.web.na/?cat=24">informante</source><ns1language>en</ns1language><category>AIDS-HIV</category><category>Tuberculosis</category><category ns0trigger="leprosy[2]; ">Leprosy</category><category>WHO</category><ns0entity id="1744" name="Social Services">Social Services</ns0entity><ns0entity id="22487" name="World Health Organization">World Health Organisation</ns0entity><ns0entity id="22487" name="World Health Organization">WHO</ns0entity><ns0entity id="1537582" name="Maria David">Maria David</ns0entity><ns0entity id="2550255" name="Health and Social Services">Health and Social Services</ns0entity><ns0entity id="53103" name="Health Organisation">Health Organisation</ns0entity><georss>-18.50000 17.08333</georss></item><item><title>Independiente Rivadavia sigue tropezando con la misma piedra</title><link>https://www.diariouno.com.ar/ovacion/futbol/independiente-rivadavia-sigue-tropezando-la-misma-piedra-n1086726</link><ns0keywords>independiente rivadavia,piedra,tabla de posiciones,virtudes del equipo,santiago moya,falencias y hablamos,rivadavia sigue tropezando,gol,fecha tras fecha,nacional,hora de atacar,cuesta esa tarea</ns0keywords><pubDate>Tue, 28 Mar 2023 21:55:00 +0200</pubDate><guid isPermaLink="false">diariouno-b33fec1abb2b29e97aa7677c1603529b</guid><source country="AR" url="https://www.diariouno.com.ar">diariouno</source><ns1language>es</ns1language><category ns0trigger="Lepra[1]; ">Leprosy</category><ns0entity id="2345317" name="Lucas Novelli">Lucas Novelli</ns0entity><ns0entity id="2943431" name="Sebastián Zunino">Sebastián Zunino</ns0entity><georss>-24.18552 -62.88535</georss></item><item><title>Leprosy, scabies and yaws: Togo's neglected tropical skin diseases need attention, says study 3 minutes ago</title><link>https://medicalxpress.com/news/2023-03-leprosy-scabies-yaws-togo-neglected.html</link><ns0keywords>study,togo,neglected tropical diseases,leprosy,informatics research unit,scabies and yaws,michael head,palokinam pitche,tropical skin diseases,conversation location,togo's neglected tropical,neglected tropical skin</ns0keywords><pubDate>Tue, 28 Mar 2023 18:55:00 +0200</pubDate><guid isPermaLink="false">medicalxpress-634ff88942b2684f88d0900feb8b5ec4</guid><source country="US" url="https://medicalxpress.com/research-news/">medicalxpress</source><ns1language>en</ns1language><category>Buruliulcer</category><category>Filariasis</category><category>Scabies</category><category>WHO</category><category>undernutrition</category><category ns0trigger="leprosy[2]; Leprosy[2]; ">Leprosy</category><category>Onchocerciasis</category><category>Yaws</category><category>ArtificialTissuesAdverseEffects</category><ns0entity id="22487" name="World Health Organization">World Health Organization</ns0entity><ns0entity id="22487" name="World Health Organization">WHO</ns0entity><ns0entity id="922470" name="Michael Head">Michael Head</ns0entity><ns0entity id="2294046" name="University of Southampton">University of Southampton</ns0entity><georss>6.12874 1.22154</georss></item><item><title>Essere un bambino disabile in Camerun, e nella maggior parte dei paesi più poveri del mondo, significa non avere la possibilità di accedere ai servizi medici. Non poter frequentare la scuola e non poter ricevere un’adeguata nutrizione. Significa essere un bambino “invisibile”, condannato a emarginazione e abbandono spesso dalla propria famiglia.</title><link>https://www.zazoom.it/2023-03-28/essere-un-bambino-disabile-in-camerun-e-nella-maggior-parte-dei-paesi-piu-poveri-del-mondo-significa-non-avere-la-possibilita-di-accedere-ai-servizi-medici-non-poter-frequentare-la-scuola-e-non-pot/12637369/</link><ns0keywords>bambino disabile,possibilità di accedere,accedere ai servizi,poter ricevere un'adeguata,significa,disabile in camerun,paesi più poveri,servizi medici,frequentare la scuola,condannato a emarginazione,maggior,italiana dokita provano,emarginazione e abbandono,ricevere un'adeguata nutrizione</ns0keywords><pubDate>Tue, 28 Mar 2023 17:20:00 +0200</pubDate><guid isPermaLink="false">zazoom-it-7ed2417bcab5215c3ad06005f628aeec</guid><source country="IT" url="https://feeds.feedburner.com/ZazoomSocialBlog-UiltmaOra">zazoom-it</source><ns1language>it</ns1language><category ns0trigger="lebbra[1]; ">Leprosy</category><category>Measles</category><georss>3.86667 11.51667</georss></item><item><title>26,371 cases of Tuberculosis diagnosed in Kano last year</title><link>https://guardian.ng/news/26371-cases-of-tuberculosis-diagnosed-in-kano-last-year/</link><ns0keywords>cases of tuberculosis,treatment success rate,kncv tuberculosis foundation,kano state,26,371 cases,tuberculosis diagnosed,leprosy control programme,kano last year,diagnosed in kano,local government areas,10 15 percent,diagnostic,percent tb cases</ns0keywords><pubDate>Tue, 28 Mar 2023 17:08:00 +0200</pubDate><guid isPermaLink="false">guardian-ng-e04dcbc3bfe56d5df2e238db3ff844ac</guid><source country="NG" url="https://guardian.ng/">guardian-ng</source><ns1language>en</ns1language><category ns0trigger="Leprosy[1]; ">Leprosy</category><category>Tuberculosis</category><ns0entity id="2751370" name="Senior Program">Senior Program</ns0entity><ns0entity id="988552" name="Facebook">Facebook</ns0entity><ns0entity id="70970" name="The Guardian">The Guardian</ns0entity><georss>12.00012 8.51672</georss></item><item><title>La fantasmal expulsión de Moya que perjudicó a la Lepra</title><link>https://www.mdzol.com/deportes/2023/3/28/la-fantasmal-expulsion-de-moya-que-perjudico-la-lepra-solo-vio-el-arbitro-325511.html</link><ns0keywords>lepra,fantasmal expulsión,moya que perjudicó,córdoba llevaba,defensor santiago moya,franco coronel,expulsión de moya,racing de córdoba,sebastián zunino,partido entre independiente,cortó leandro fernández,minutos de juego,llevaba apenas 19,jugada</ns0keywords><pubDate>Tue, 28 Mar 2023 16:15:00 +0200</pubDate><guid isPermaLink="false">mdzol-b12e001eeaf611acaae85320b4efdced</guid><source country="AR" url="https://www.mdzol.com/">mdzol</source><ns1language>es</ns1language><category ns0trigger="Lepra[4]; ">Leprosy</category><ns0entity id="218434" name="Leandro Fernandez">Leandro Fernández</ns0entity><ns0entity id="2125986" name="Luciano Abecasis">Luciano Abecasis</ns0entity><ns0entity id="2943431" name="Sebastián Zunino">Sebastián Zunino</ns0entity><ns0entity id="3068818" name="Racing de Córdoba">Racing de Córdoba</ns0entity><georss>-12.30967 44.43685</georss></item><item><title>Juan Manuel Elordi levantó el Gargantini con su gol</title><link>https://www.diariouno.com.ar/ovacion/futbol/juan-manuel-elordi-levanto-el-gargantini-su-gol-independiente-rivadavia-n1086526</link><ns0keywords>juan manuel elordi,levantó el gargantini,racing de córdoba,estadio bautista gargantini,manuel elordi levantó,santiago moya,rivadavia juan manuel,luciano abecasis,independiente rivadavia juan,defensor de independiente,interesar,marcó el gol,expulsión</ns0keywords><pubDate>Tue, 28 Mar 2023 16:01:00 +0200</pubDate><guid isPermaLink="false">diariouno-0217d31ee0ba6cc3f24e6576f601ab3c</guid><source country="AR" url="https://www.diariouno.com.ar">diariouno</source><ns1language>es</ns1language><category ns0trigger="Lepra[1]; ">Leprosy</category><ns0entity id="3097583" name="Deportivo Riestra">Deportivo Riestra</ns0entity><ns0entity id="2125986" name="Luciano Abecasis">Luciano Abecasis</ns0entity><ns0entity id="3068818" name="Racing de Córdoba">Racing de Córdoba</ns0entity><georss>-34.61315 -58.37723</georss></item><item><title>Ignacio Astore, presidente de Newell's, y el sueño de repatriar a Messi: ¿son sólo sueños?</title><link>https://www.clarin.com/deportes/ignacio-astore-presidente-newell-s-sueno-repatriar-messi-solo-suenos-_0_h0GyueXdVF.html</link><ns0keywords>ignacio astore,presidente de newell's,sueño de repatriar,maxi rodríguez,repatriar a messi,copa libertadores,sueños,jugador,vuelta de messi,fútbol sudamericano,argentino,previa del sorteo</ns0keywords><pubDate>Tue, 28 Mar 2023 15:43:00 +0200</pubDate><guid isPermaLink="false">clarin-71ab3ab79caf911e694ab2a11fc2498c</guid><source country="AR" url="https://www.clarin.com/rss/lo-ultimo/">clarin</source><ns1language>es</ns1language><category ns0trigger="Lepra[1]; ">Leprosy</category><ns0entity id="2257584" name="TyC Sports">TyC Sports</ns0entity><ns0entity id="58084" name="Maxi Rodriguez">Maxi Rodríguez</ns0entity><ns0entity id="66075" name="Lionel Messi">Messi</ns0entity><ns0entity id="2922487" name="Ignacio Astore">Ignacio Astore</ns0entity><georss>-32.94682 -60.63932</georss></item><item><title>Nanomaterials, Vol. 13, Pages 1204: Application of Covalent Organic Frameworks (COFs) as Dyes and Additives for Dye-Sensitized Solar Cells (DSSCs)</title><link>https://www.mdpi.com/2079-4991/13/7/1204</link><ns0keywords>covalent organic frameworks,dye-sensitized solar cells,vol,dyes and additives,organic frameworks cofs,reticular innovative organic,solar cells dsscs,min,reactor,added,pages 1204,bismarck brown,additives for dye-sensitized</ns0keywords><pubDate>Tue, 28 Mar 2023 14:50:00 +0200</pubDate><guid isPermaLink="false">mdpi-9903829e80dace5880902ad5e35723a2</guid><source country="CH" url="https://www.mdpi.com/rss">mdpi</source><ns1language>en</ns1language><category>Nanomaterials</category><category ns0trigger="leprosy[1]; ">Leprosy</category><category>HydrogeneChloride</category><ns0entity id="139894" name="Honeywell International">Honeywell</ns0entity><ns0entity id="2828078" name="Sigma Aldrich">Sigma-Aldrich</ns0entity><georss>46.80833 -100.78374</georss></item><item><title>OMS incentiva integração na resposta a doenças tropicais negligenciadas de pele</title><link>https://www.progresso.com.br/sociedade/saude/oms-incentiva-integracao-na-resposta-a-doencas-tropicais/398353/</link><ns0keywords>doenças tropicais negligenciadas,negligenciadas de pele,oms incentiva integração,resposta a doenças,integração na resposta,hanseníase,estigma,agência da onu,pessoas,saúde oms incentiva,países</ns0keywords><pubDate>Tue, 28 Mar 2023 14:25:00 +0200</pubDate><guid isPermaLink="false">progresso-367142c35d317e7dcb37be71fec8dd94</guid><source country="BR" url="https://www.progresso.com.br/">progresso</source><ns1language>pt</ns1language><category>CoronavirusInfection</category><category ns0trigger="Hanseníase[1]; hanseníase[4]; ">Leprosy</category><category>Buruliulcer</category><category>Tropicaldiseases</category><ns0entity id="3202" name="United Nations">ONU</ns0entity><ns0entity id="3202" name="United Nations">Nações Unidas</ns0entity><ns0entity id="2338337" name="Artur Custodio">Artur Custodio</ns0entity><ns0entity id="22487" name="World Health Organization">OMS</ns0entity><ns0entity id="22487" name="World Health Organization">Organização Mundial da Saúde</ns0entity><ns0entity id="585360" name="Ibrahima Fall">Ibrahima Fall</ns0entity><ns0entity id="2528522" name="Coronavirus">Covid-19</ns0entity><georss>64.00000 -19.00000</georss></item><item><title>Astore y la Sudamericana: el dinero, la mirada de Heinze y el sueño de Messi</title><link>https://www.cadena3.com/noticia/radioinforme-3-rosario/astore-y-la-sudamericana-el-dinero-la-mirada-de-heinze-y-el-sueno-de-messi_353682</link><ns0keywords>mirada de heinze,ignacio astore,sueño de messi,rosario y tocó,dialogó con cadena,jugamos copa sudamericana,tocó varios temas,presidente de newell's,finales de libertadores,dinero,cadena 3 rosario,tradición copera</ns0keywords><pubDate>Tue, 28 Mar 2023 14:24:00 +0200</pubDate><guid isPermaLink="false">cadena3-357f0f0013416dded61e0e78dfd02f52</guid><source country="AR" url="http://www.cadena3.com">cadena3</source><ns1language>es</ns1language><category ns0trigger="Lepra[1]; ">Leprosy</category><ns0entity id="66075" name="Lionel Messi">Messi</ns0entity><ns0entity id="66075" name="Lionel Messi">Lionel Messi</ns0entity><ns0entity id="2922487" name="Ignacio Astore">Ignacio Astore</ns0entity><georss>-32.94682 -60.63932</georss></item><item><title>Ever Demaldé se fue conforme con la entrega de los jugadores de la Lepra</title><link>https://www.diariouno.com.ar/ovacion/futbol/ever-demalde-se-fue-conforme-la-entrega-los-jugadores-independiente-rivadavia-n1086524</link><ns0keywords>rivadavia ever demaldé,racing de córdoba,jugadores,lepra,estadio bautista gargantini,merecieron ganar,juega independiente rivadavia,independiente rivadavia ever,ganar y destacó,entrenador de independiente,entrega,conforme,partidos</ns0keywords><pubDate>Tue, 28 Mar 2023 12:52:00 +0200</pubDate><guid isPermaLink="false">diariouno-31c67c5621f6fe5a9f43cbdb9c69a167</guid><source country="AR" url="https://www.diariouno.com.ar">diariouno</source><ns1language>es</ns1language><category ns0trigger="Lepra[2]; ">Leprosy</category><ns0entity id="3097583" name="Deportivo Riestra">Deportivo Riestra</ns0entity><ns0entity id="3068818" name="Racing de Córdoba">Racing de Córdoba</ns0entity><georss>-24.18552 -62.88535</georss></item><item><title>Domínguez arrancó la semana probando y aún mantiene varias dudas</title><link>https://www.eldia.com/nota/2023-3-28-5-28-21-dominguez-arranco-la-semana-probando-y-aun-mantiene-varias-dudas-deportes</link><ns0keywords>arrancó la semana,mantiene varias dudas,viernes ante newells,sufrida ante gimnasia,semana probando,técnico eduardo domínguez,tareas futbolísticas probando,estudiantes comenzó,domínguez arrancó,semana de tareas,profesional de estudiantes,plantel profesional,leo godoy seguirá,santiago ascacibar,zuqui o sosa</ns0keywords><pubDate>Tue, 28 Mar 2023 10:45:00 +0200</pubDate><guid isPermaLink="false">eldia-AR-f5681fcc5dc5092de774df242ec00a56</guid><source country="AR" url="https://www.eldia.com/">eldia-AR</source><ns1language>es</ns1language><category ns0trigger="Lepra[1]; ">Leprosy</category><ns0entity id="3002972" name="Fabricio Iacovich">Fabricio Iacovich</ns0entity><ns0entity id="27829" name="Jorge Rodriguez">Jorge Rodríguez</ns0entity><ns0entity id="476110" name="Eduardo Dominguez">Eduardo Domínguez</ns0entity><ns0entity id="2020194" name="Emmanuel Mas">Emmanuel Mas</ns0entity><ns0entity id="2095425" name="Santiago Ascacibar">Santiago Ascacibar</ns0entity></item><item><title>Leprosy, scabies and yaws — Togo’s neglected tropical skin diseases need attention</title><link>https://www.downtoearth.org.in/blog/africa/leprosy-scabies-and-yaws-togo-s-neglected-tropical-skin-diseases-need-attention-88496</link><ns0keywords>togo's neglected tropical,found,leprosy,cent,world health organization,cases,yaws togo's neglected,tropical skin diseases,study,africa,scabies and yaws</ns0keywords><pubDate>Tue, 28 Mar 2023 09:45:00 +0200</pubDate><guid isPermaLink="false">agrarszektor-cf5b72c2cc845f0098ca3f4cc89fe96b</guid><source country="HU" url="https://www.downtoearth.org.in/blog">agrarszektor</source><ns1language>en</ns1language><category>Buruliulcer</category><category>Filariasis</category><category>Scabies</category><category>WHO</category><category>undernutrition</category><category ns0trigger="leprosy[2]; Leprosy[1]; ">Leprosy</category><category>Onchocerciasis</category><category>Yaws</category><category>ArtificialTissuesAdverseEffects</category><ns0entity id="22487" name="World Health Organization">World Health Organization</ns0entity><ns0entity id="22487" name="World Health Organization">WHO</ns0entity><georss>6.12874 1.22154</georss></item><item><title>Estudiantes se entrena con el foco puesto en Newell's</title><link>https://diariohoy.net/el-clasico/estudiantes-se-entrena-con-el-foco-puesto-en-newells-224371</link><ns0keywords>foco puesto,estudiantes se entrena,doble fecha fifa,plantel de estudiantes,puesto en newell's,domingo libre,semana sin actividad,entrenador eduardo domínguez,leonardo godoy,estudiantes volvió,domínguez ya piensa,puso la mira,mira de lleno</ns0keywords><pubDate>Tue, 28 Mar 2023 09:27:00 +0200</pubDate><guid isPermaLink="false">diariohoy-b488a4c07e6c349d327e5cec0ad0f7d3</guid><source country="AR" url="https://diariohoy.net/">diariohoy</source><ns1language>es</ns1language><category ns0trigger="Lepra[1]; ">Leprosy</category><ns0entity id="421670" name="FIFA">FIFA</ns0entity><ns0entity id="2976653" name="Franco Zapiola">Franco Zapiola</ns0entity><ns0entity id="27829" name="Jorge Rodriguez">Jorge Rodríguez</ns0entity><ns0entity id="2775516" name="Leonardo Godoy">Leonardo Godoy</ns0entity><ns0entity id="2084247" name="Matias Godoy">Matías Godoy</ns0entity><ns0entity id="476110" name="Eduardo Dominguez">Eduardo Domínguez</ns0entity><ns0entity id="1876501" name="Luciano Lollo">Luciano Lollo</ns0entity><ns0entity id="2979350" name="Zaid Romero">Zaid Romero</ns0entity><ns0entity id="223198" name="Mariano Gonzalo Andujar">Mariano Andújar</ns0entity><ns0entity id="2095425" name="Santiago Ascacibar">Santiago Ascacíbar</ns0entity><ns0entity id="556166" name="Mauro Boselli">Mauro Boselli</ns0entity><ns0entity id="2012881" name="Fernando Zuqui">Fernando Zuqui</ns0entity><georss>21.12908 -101.67374</georss></item><item><title>TB Fight, Leprosy Elimination Needs More Investment</title><link>https://allafrica.com/stories/202303280060.html</link><ns0keywords>health halima daudi,malawi,deputy minister,tb fight,leprosy elimination day,tb and leprosy,tuberculosis tb,minister of health,investment in efforts,national professional officer,world health organization,fight against tuberculosis</ns0keywords><pubDate>Tue, 28 Mar 2023 08:44:00 +0200</pubDate><guid isPermaLink="false">allafrica-a6b06398fc89e39529290406c34db276</guid><source country="US" url="https://allafrica.com/tools/headlines/rdf/malawi/headlines.rdf">allafrica</source><ns1language>en</ns1language><category ns0trigger="leprosy[6]; Leprosy[3]; ">Leprosy</category><category>Tuberculosis</category><category>WHO</category><ns0entity id="22487" name="World Health Organization">World Health Organization</ns0entity><ns0entity id="22487" name="World Health Organization">WHO</ns0entity><georss>-13.79841 32.88019</georss></item><item><title>As told to Parliament (March 24, 2023): India has eliminated leprosy, as per WHO criterion</title><link>https://www.downtoearth.org.in/news/governance/as-told-to-parliament-march-24-2023-india-has-eliminated-leprosy-as-per-who-criterion-88467</link><ns0keywords>lok sabha,union minister,mansukh mandaviya told,told to parliament,health organization criterion,told the lok,parliament march 24,family welfare mansukh,global gender gap,public health problem,india has eliminated,national family health,eliminated leprosy</ns0keywords><pubDate>Tue, 28 Mar 2023 07:34:00 +0200</pubDate><guid isPermaLink="false">downtoearth-89ceb4b78753bdf2b0e7953d9793abcb</guid><source country="IN" url="https://www.downtoearth.org.in/rss/all">downtoearth</source><ns1language>en</ns1language><category>WHO</category><category>undernutrition</category><category ns0trigger="leprosy[2]; Leprosy[1]; ">Leprosy</category><category>Arsenic</category><ns0entity id="2939501" name="Mansukh Mandaviya">Mansukh Mandaviya</ns0entity><ns0entity id="136448" name="Economic Forum">Economic Forum</ns0entity><ns0entity id="2260961" name="Industrial Research">Industrial Research</ns0entity><ns0entity id="9158" name="Lok Sabha">Lok Sabha</ns0entity><ns0entity id="39174" name="Narendra Singh">Narendra Singh</ns0entity><ns0entity id="2113927" name="Management Information Systems">Management Information System</ns0entity><ns0entity id="523950" name="World Economic Forum">World Economic Forum</ns0entity><ns0entity id="2258803" name="Ministry of Health and Family Welfare">Ministry of Health and Family Welfare</ns0entity><ns0entity id="86933" name="Rajya Sabha">Rajya Sabha</ns0entity><ns0entity id="2468720" name="Ministry of Health">Ministry of Health</ns0entity><ns0entity id="22487" name="World Health Organization">WHO</ns0entity><ns0entity id="22487" name="World Health Organization">World Health Organization</ns0entity><ns0entity id="2439922" name="Women and Child Development">Women and Child Development</ns0entity><ns0entity id="2261434" name="Indian Council">Indian Council</ns0entity><georss>26.00000 93.00000</georss></item><item><title>Bauchi detects 7,806 cases of tuberculosis</title><link>https://punchng.com/bauchi-detects-7806-cases-of-tuberculosis/</link><ns0keywords>bauchi state,world tuberculosis day,executive secretary,cases of tuberculosis,detects 7,806 cases,tuberculosis control programme,news conference,bauchi detects 7,806,tuberculosis in 2022,sani mohammad,state reportedly recorded,leprosy and malaria,reportedly recorded 7,806,recorded 7,806 cases</ns0keywords><pubDate>Tue, 28 Mar 2023 07:05:00 +0200</pubDate><guid isPermaLink="false">punchng-7138ffedcb0c78ad841a90b0dfb182e7</guid><source country="NG" url="https://punchng.com/topics/news/">punchng</source><ns1language>en</ns1language><category>CoronavirusInfection</category><category ns0trigger="Leprosy[1]; ">Leprosy</category><category>Tuberculosis</category><category>WHO</category><category>AIDS-HIV</category><category>Malaria</category><ns0entity id="2090589" name="State Agency">State Agency</ns0entity><ns0entity id="2173282" name="Yakubu Abdullahi">Yakubu Abdullahi</ns0entity><ns0entity id="22487" name="World Health Organization">WHO</ns0entity><ns0entity id="134782" name="Prophet Muhammad">Mohammad</ns0entity><ns0entity id="2528522" name="Coronavirus">COVID-19</ns0entity><georss>10.31032 9.84388</georss></item><item><title>Leprosy, Scabies and Yaws - Togo's Neglected Tropical Skin Diseases Need Attention</title><link>https://allafrica.com/stories/202303280031.html</link><ns0keywords>togo's neglected tropical,leprosy,children,scabies,cases,attention,neglected tropical diseases,found,yaws togo's neglected,study,tropical skin diseases,africa</ns0keywords><pubDate>Tue, 28 Mar 2023 06:53:00 +0200</pubDate><guid isPermaLink="false">allafrica-21aa949939891d4e02b49223fa59fe8d</guid><source country="US" url="https://allafrica.com/tools/headlines/rdf/togo/headlines.rdf">allafrica</source><ns1language>en</ns1language><category>Buruliulcer</category><category>Scabies</category><category>WHO</category><category>undernutrition</category><category ns0trigger="leprosy[1]; Leprosy[1]; ">Leprosy</category><category>Yaws</category><category>ArtificialTissuesAdverseEffects</category><ns0entity id="22487" name="World Health Organization">WHO</ns0entity><georss>6.12874 1.22154</georss></item><item><title>La Lepra y un punto con sabor a muy poco</title><link>https://cuyonoticias.com/contenido/8392/la-lepra-y-un-punto-con-sabor-a-muy-poco</link><ns0keywords>independiente rivadavia,lepra,racing de córdoba,punto con sabor,juan cruz bolado,francisco,indebida expulsión,bautista gargantini,travesaño,juan manuel elordi,mala fortuna bola,local,abecasis</ns0keywords><pubDate>Tue, 28 Mar 2023 06:22:00 +0200</pubDate><guid isPermaLink="false">cuyonoticias-5618e434bb37f0a4975f08d3a62370ed</guid><source country="AR" url="https://cuyonoticias.com/">cuyonoticias</source><ns1language>es</ns1language><category ns0trigger="Lepra[1]; ">Leprosy</category><ns0entity id="218434" name="Leandro Fernandez">Leandro Fernández</ns0entity><ns0entity id="2125986" name="Luciano Abecasis">Luciano Abecasis</ns0entity><ns0entity id="2271968" name="Rodrigo Acosta">Rodrigo Acosta</ns0entity><ns0entity id="2142180" name="Joaquín Mateo">Joaquín Mateo</ns0entity><ns0entity id="2943431" name="Sebastián Zunino">Sebastián Zunino</ns0entity><ns0entity id="3292029" name="Emmanuel Gimenez">Emmanuel Giménez</ns0entity><ns0entity id="410569" name="Carlos Bossio">Carlos Bossio</ns0entity><ns0entity id="2742332" name="Juan Cruz Bolado">Juan Cruz Bolado</ns0entity><ns0entity id="106105" name="Juan Cruz">Juan Cruz</ns0entity><ns0entity id="1900871" name="Ezequiel Ham">Ezequiel Ham</ns0entity><ns0entity id="182584" name="Pablo Lopez">Pablo López</ns0entity><ns0entity id="2047748" name="Franco Romero">Franco Romero</ns0entity><ns0entity id="3068818" name="Racing de Córdoba">Racing de Córdoba</ns0entity><georss>-12.30967 44.43685</georss></item><item><title>Primera Nacional. Racing no pasó del empate ante Independiente Rivadavia</title><link>https://hoydia.com.ar/deportes/racing-no-paso-del-empate-ante-independiente-rivadavia/</link><ns0keywords>independiente rivadavia,nacional,juan manuel elordi,racing no pasó,pasó del empate,santiago moya,empate ante independiente,franco coronel,10 minutos,zona b,carlos bossio,séptima fecha,italia igualó,rivadavia de mendoza</ns0keywords><pubDate>Tue, 28 Mar 2023 05:12:00 +0200</pubDate><guid isPermaLink="false">hoydia-2aa8f102d671bcd36ceaa10dd57da97e</guid><source country="AR" url="https://www.hoydia.com.ar/index.php">hoydia</source><ns1language>es</ns1language><category ns0trigger="Lepra[1]; ">Leprosy</category><ns0entity id="2181659" name="Rivadavia de Mendoza">Rivadavia de Mendoza</ns0entity><ns0entity id="410569" name="Carlos Bossio">Carlos Bossio</ns0entity><georss>18.48333 -69.93333</georss></item></data>